nxquickplot/__init__.py
nxquickplot-1.0.0.dist-info/LICENSE
nxquickplot-1.0.0.dist-info/METADATA
nxquickplot-1.0.0.dist-info/WHEEL
nxquickplot-1.0.0.dist-info/top_level.txt
nxquickplot-1.0.0.dist-info/RECORD
